<?xml version="1.0"?>
<image xmlns="http://www.vips.ecs.soton.ac.uk//dzsave" date="2025-06-03T19:33:44.037517+12" version="8.16.1">
  <properties>
    <property>
      <name>width</name>
      <value type="gint">14422</value>
    </property>
    <property>
      <name>height</name>
      <value type="gint">5273</value>
    </property>
    <property>
      <name>bands</name>
      <value type="gint">3</value>
    </property>
    <property>
      <name>xoffset</name>
      <value type="gint">0</value>
    </property>
    <property>
      <name>yoffset</name>
      <value type="gint">0</value>
    </property>
    <property>
      <name>xres</name>
      <value type="gdouble">9.4488188976377963</value>
    </property>
    <property>
      <name>yres</name>
      <value type="gdouble">9.4488188976377963</value>
    </property>
    <property>
      <name>vips-loader</name>
      <value type="VipsRefString">jpegload</value>
    </property>
    <property>
      <name>jpeg-multiscan</name>
      <value type="gint">0</value>
    </property>
    <property>
      <name>jpeg-chroma-subsample</name>
      <value type="VipsRefString">4:4:4</value>
    </property>
    <property>
      <name>resolution-unit</name>
      <value type="VipsRefString">in</value>
    </property>
    <property>
      <name>exif-ifd0-Make</name>
      <value type="VipsRefString">SONY (SONY, ASCII, 5 components, 5 bytes)</value>
    </property>
    <property>
      <name>exif-ifd0-Model</name>
      <value type="VipsRefString">ILCE-7M3 (ILCE-7M3, ASCII, 9 components, 9 bytes)</value>
    </property>
    <property>
      <name>exif-ifd0-XResolution</name>
      <value type="VipsRefString">240/1 (240, Rational, 1 components, 8 bytes)</value>
    </property>
    <property>
      <name>exif-ifd0-YResolution</name>
      <value type="VipsRefString">240/1 (240, Rational, 1 components, 8 bytes)</value>
    </property>
    <property>
      <name>exif-ifd0-ResolutionUnit</name>
      <value type="VipsRefString">2 (Inch, Short, 1 components, 2 bytes)</value>
    </property>
    <property>
      <name>exif-ifd0-Software</name>
      <value type="VipsRefString">Adobe Photoshop Lightroom Classic 14.3.1 (Macintosh) (Adobe Photoshop Lightroom Classic 14.3.1 (Macintosh), ASCII, 53 components, 53 bytes)</value>
    </property>
    <property>
      <name>exif-ifd0-DateTime</name>
      <value type="VipsRefString">2025:06:02 12:43:03 (2025:06:02 12:43:03, ASCII, 20 components, 20 bytes)</value>
    </property>
    <property>
      <name>exif-ifd0-Artist</name>
      <value type="VipsRefString">Derek Thatcher (Derek Thatcher, ASCII, 15 components, 15 bytes)</value>
    </property>
    <property>
      <name>exif-ifd0-Copyright</name>
      <value type="VipsRefString">Derek Thatcher  (Derek Thatcher , ASCII, 15 components, 15 bytes)</value>
    </property>
    <property>
      <name>exif-ifd1-Compression</name>
      <value type="VipsRefString">6 (JPEG compression, Short, 1 components, 2 bytes)</value>
    </property>
    <property>
      <name>exif-ifd1-XResolution</name>
      <value type="VipsRefString">72/1 (72, Rational, 1 components, 8 bytes)</value>
    </property>
    <property>
      <name>exif-ifd1-YResolution</name>
      <value type="VipsRefString">72/1 (72, Rational, 1 components, 8 bytes)</value>
    </property>
    <property>
      <name>exif-ifd1-ResolutionUnit</name>
      <value type="VipsRefString">2 (Inch, Short, 1 components, 2 bytes)</value>
    </property>
    <property>
      <name>exif-ifd2-ExposureTime</name>
      <value type="VipsRefString">1/500 (1/500 sec., Rational, 1 components, 8 bytes)</value>
    </property>
    <property>
      <name>exif-ifd2-FNumber</name>
      <value type="VipsRefString">67/10 (f/6.7, Rational, 1 components, 8 bytes)</value>
    </property>
    <property>
      <name>exif-ifd2-ExposureProgram</name>
      <value type="VipsRefString">2 (Normal program, Short, 1 components, 2 bytes)</value>
    </property>
    <property>
      <name>exif-ifd2-ISOSpeedRatings</name>
      <value type="VipsRefString">400 (400, Short, 1 components, 2 bytes)</value>
    </property>
    <property>
      <name>exif-ifd2-SensitivityType</name>
      <value type="VipsRefString">2 (Recommended exposure index (REI), Short, 1 components, 2 bytes)</value>
    </property>
    <property>
      <name>exif-ifd2-RecommendedExposureIndex</name>
      <value type="VipsRefString">400 (400, Long, 1 components, 4 bytes)</value>
    </property>
    <property>
      <name>exif-ifd2-ExifVersion</name>
      <value type="VipsRefString">Exif Version 2.31 (Exif Version 2.31, Undefined, 4 components, 4 bytes)</value>
    </property>
    <property>
      <name>exif-ifd2-DateTimeOriginal</name>
      <value type="VipsRefString">2025:05:31 16:32:17 (2025:05:31 16:32:17, ASCII, 20 components, 20 bytes)</value>
    </property>
    <property>
      <name>exif-ifd2-DateTimeDigitized</name>
      <value type="VipsRefString">2025:05:31 16:32:17 (2025:05:31 16:32:17, ASCII, 20 components, 20 bytes)</value>
    </property>
    <property>
      <name>exif-ifd2-OffsetTime</name>
      <value type="VipsRefString">+12:00 (+12:00, ASCII, 7 components, 7 bytes)</value>
    </property>
    <property>
      <name>exif-ifd2-OffsetTimeOriginal</name>
      <value type="VipsRefString">+13:00 (+13:00, ASCII, 7 components, 7 bytes)</value>
    </property>
    <property>
      <name>exif-ifd2-OffsetTimeDigitized</name>
      <value type="VipsRefString">+13:00 (+13:00, ASCII, 7 components, 7 bytes)</value>
    </property>
    <property>
      <name>exif-ifd2-ShutterSpeedValue</name>
      <value type="VipsRefString">8965784/1000000 (8.97 EV (1/500 sec.), SRational, 1 components, 8 bytes)</value>
    </property>
    <property>
      <name>exif-ifd2-ApertureValue</name>
      <value type="VipsRefString">5488322/1000000 (5.49 EV (f/6.7), Rational, 1 components, 8 bytes)</value>
    </property>
    <property>
      <name>exif-ifd2-BrightnessValue</name>
      <value type="VipsRefString">19784/2560 (7.73 EV (726.47 cd/m^2), SRational, 1 components, 8 bytes)</value>
    </property>
    <property>
      <name>exif-ifd2-ExposureBiasValue</name>
      <value type="VipsRefString">-3/10 (-0.30 EV, SRational, 1 components, 8 bytes)</value>
    </property>
    <property>
      <name>exif-ifd2-MaxApertureValue</name>
      <value type="VipsRefString">1404/256 (5.48 EV (f/6.7), Rational, 1 components, 8 bytes)</value>
    </property>
    <property>
      <name>exif-ifd2-MeteringMode</name>
      <value type="VipsRefString">5 (Pattern, Short, 1 components, 2 bytes)</value>
    </property>
    <property>
      <name>exif-ifd2-LightSource</name>
      <value type="VipsRefString">0 (Unknown, Short, 1 components, 2 bytes)</value>
    </property>
    <property>
      <name>exif-ifd2-Flash</name>
      <value type="VipsRefString">16 (16, Short, 1 components, 2 bytes)</value>
    </property>
    <property>
      <name>exif-ifd2-FocalLength</name>
      <value type="VipsRefString">5000/10 (500.0 mm, Rational, 1 components, 8 bytes)</value>
    </property>
    <property>
      <name>exif-ifd2-SubSecTimeOriginal</name>
      <value type="VipsRefString">1 (1, ASCII, 2 components, 2 bytes)</value>
    </property>
    <property>
      <name>exif-ifd2-SubSecTimeDigitized</name>
      <value type="VipsRefString">1 (1, ASCII, 2 components, 2 bytes)</value>
    </property>
    <property>
      <name>exif-ifd2-ColorSpace</name>
      <value type="VipsRefString">1 (sRGB, Short, 1 components, 2 bytes)</value>
    </property>
    <property>
      <name>exif-ifd2-FocalPlaneXResolution</name>
      <value type="VipsRefString">54965632/32768 (1677.41797, Rational, 1 components, 8 bytes)</value>
    </property>
    <property>
      <name>exif-ifd2-FocalPlaneYResolution</name>
      <value type="VipsRefString">54965632/32768 (1677.41797, Rational, 1 components, 8 bytes)</value>
    </property>
    <property>
      <name>exif-ifd2-FocalPlaneResolutionUnit</name>
      <value type="VipsRefString">3 (Centimeter, Short, 1 components, 2 bytes)</value>
    </property>
    <property>
      <name>exif-ifd2-FileSource</name>
      <value type="VipsRefString">DSC (DSC, Undefined, 1 components, 1 bytes)</value>
    </property>
    <property>
      <name>exif-ifd2-SceneType</name>
      <value type="VipsRefString">Directly photographed (Directly photographed, Undefined, 1 components, 1 bytes)</value>
    </property>
    <property>
      <name>exif-ifd2-CustomRendered</name>
      <value type="VipsRefString">0 (Normal process, Short, 1 components, 2 bytes)</value>
    </property>
    <property>
      <name>exif-ifd2-ExposureMode</name>
      <value type="VipsRefString">0 (Auto exposure, Short, 1 components, 2 bytes)</value>
    </property>
    <property>
      <name>exif-ifd2-WhiteBalance</name>
      <value type="VipsRefString">0 (Auto white balance, Short, 1 components, 2 bytes)</value>
    </property>
    <property>
      <name>exif-ifd2-DigitalZoomRatio</name>
      <value type="VipsRefString">16/16 (1.00, Rational, 1 components, 8 bytes)</value>
    </property>
    <property>
      <name>exif-ifd2-FocalLengthIn35mmFilm</name>
      <value type="VipsRefString">500 (500, Short, 1 components, 2 bytes)</value>
    </property>
    <property>
      <name>exif-ifd2-SceneCaptureType</name>
      <value type="VipsRefString">0 (Standard, Short, 1 components, 2 bytes)</value>
    </property>
    <property>
      <name>exif-ifd2-Contrast</name>
      <value type="VipsRefString">0 (Normal, Short, 1 components, 2 bytes)</value>
    </property>
    <property>
      <name>exif-ifd2-Saturation</name>
      <value type="VipsRefString">0 (Normal, Short, 1 components, 2 bytes)</value>
    </property>
    <property>
      <name>exif-ifd2-Sharpness</name>
      <value type="VipsRefString">0 (Normal, Short, 1 components, 2 bytes)</value>
    </property>
    <property>
      <name>exif-ifd2-LensSpecification</name>
      <value type="VipsRefString">1500/10 5000/10 50/10 67/10 (150.0, 500.0, 5.0, 6.7, Rational, 4 components, 32 bytes)</value>
    </property>
    <property>
      <name>exif-ifd2-LensModel</name>
      <value type="VipsRefString">E 150-500mm F5-6.7 A057 (E 150-500mm F5-6.7 A057, ASCII, 24 components, 24 bytes)</value>
    </property>
    <property>
      <name>exif-ifd2-FlashpixVersion</name>
      <value type="VipsRefString">FlashPix Version 1.0 (FlashPix Version 1.0, Undefined, 4 components, 4 bytes)</value>
    </property>
    <property>
      <name>vips-sequential</name>
      <value type="gint">1</value>
    </property>
  </properties>
</image>
